django_blogconnector/__init__.py
django_blogconnector/admin.py
django_blogconnector/apps.py
django_blogconnector/helpers.py
django_blogconnector/models.py
django_blogconnector/tests.py
django_blogconnector/urls.py
django_blogconnector/utilities.py
django_blogconnector/views.py
django_blogconnector/__pycache__/__init__.cpython-37.pyc
django_blogconnector/__pycache__/admin.cpython-37.pyc
django_blogconnector/__pycache__/models.cpython-37.pyc
django_blogconnector/__pycache__/urls.cpython-37.pyc
django_blogconnector/__pycache__/views.cpython-37.pyc
django_blogconnector/management/__init__.py
django_blogconnector/management/commands/__init__.py
django_blogconnector/management/commands/import_feed.py
django_blogconnector/migrations/0001_initial.py
django_blogconnector/migrations/0002_auto_20190510_1258.py
django_blogconnector/migrations/0003_auto_20190510_1517.py
django_blogconnector/migrations/__init__.py
django_blogconnector/migrations/__pycache__/0001_initial.cpython-37.pyc
django_blogconnector/migrations/__pycache__/0002_auto_20190510_1258.cpython-37.pyc
django_blogconnector/migrations/__pycache__/0003_auto_20190510_1517.cpython-37.pyc
django_blogconnector/migrations/__pycache__/__init__.cpython-37.pyc
django_blogconnector/templates/blog_connector/categories.html
django_blogconnector/templates/blog_connector/category.html
django_blogconnector/templates/blog_connector/category_link.html
django_blogconnector/templates/blog_connector/page.html
django_blogconnector/templates/blog_connector/post.html
django_blogconnector/templates/blog_connector/single.html
django_blogconnector/templatetags/__init__.py
django_blogconnector/templatetags/blogconnector.py
django_blogconnector/templatetags/__pycache__/__init__.cpython-37.pyc
django_blogconnector/templatetags/__pycache__/blogconnector.cpython-37.pyc
htdocs/__init__.py
htdocs/settings.py
htdocs/urls.py
htdocs/wsgi.py
django_blogconnector-1.0.0.dist-info/LICENSE
django_blogconnector-1.0.0.dist-info/METADATA
django_blogconnector-1.0.0.dist-info/WHEEL
django_blogconnector-1.0.0.dist-info/top_level.txt
django_blogconnector-1.0.0.dist-info/RECORD
