Metadata-Version: 2.1
Name: django-blogconnector
Version: 1.0.0
Summary: An easy way to show the contents of a blog in your Django app.
Home-page: https://www.github.com/avryhof/django-blogconnector
Author: Amos Vryhof
Author-email: amos@vryhofresearch.com
License: MIT License
Platform: UNKNOWN
Classifier: Environment :: Web Environment
Classifier: Framework :: Django
Classifier: Framework :: Django :: 1.8
Classifier: Intended Audience :: Developers
Classifier: License :: OSI Approved :: MIT License
Classifier: Operating System :: OS Independent
Classifier: Programming Language :: Python
Classifier: Programming Language :: Python :: 2
Classifier: Programming Language :: Python :: 2.7
Classifier: Programming Language :: Python :: 3
Classifier: Topic :: Internet :: WWW/HTTP
Classifier: Topic :: Internet :: WWW/HTTP :: Dynamic Content
Requires-Dist: Django
Requires-Dist: requests
Requires-Dist: xmltodict
